abkdependerlib/__init__.py
abkdependerlib/abkarray.py
abkdependerlib-0.0.1.dist-info/LICENSE.txt
abkdependerlib-0.0.1.dist-info/METADATA
abkdependerlib-0.0.1.dist-info/WHEEL
abkdependerlib-0.0.1.dist-info/top_level.txt
abkdependerlib-0.0.1.dist-info/RECORD
